methyl_vi/__init__.py
methyl_vi/_constants.py
methyl_vi/distributions/__init__.py
methyl_vi/distributions/_beta_binomial.py
methyl_vi/model/__init__.py
methyl_vi/model/differential.py
methyl_vi/model/methyl_vi.py
methyl_vi/model/utils.py
methyl_vi/module/__init__.py
methyl_vi/module/methyl_vi.py
methyl_vi/nn/__init__.py
methyl_vi/nn/_base_components.py
methyl_vi-0.1.0.dist-info/METADATA
methyl_vi-0.1.0.dist-info/WHEEL
methyl_vi-0.1.0.dist-info/top_level.txt
methyl_vi-0.1.0.dist-info/RECORD
